limber/__init__.py
limber/__main__.py
limber/imports/__init__.py
limber/imports/google/__init__.py
limber/imports/google/_jsii/__init__.py
limber/imports/google/_jsii/hashicorp_google@0.0.0.jsii.tgz
limber/main/__init__.py
limber/main/limber_terraform_stack.py
limber/main/dag/__init__.py
limber/main/dag/dag.py
limber/operators/__init__.py
limber/operators/operator.py
limber/operators/python_operator/__init__.py
limber/operators/python_operator/python_operator.py
limber/tests/__init__.py
limber/tests/operators/__init__.py
limber/tests/operators/test_dependencies.py
limber-0.1.9.dist-info/LICENSE
limber-0.1.9.dist-info/METADATA
limber-0.1.9.dist-info/WHEEL
limber-0.1.9.dist-info/entry_points.txt
limber-0.1.9.dist-info/top_level.txt
limber-0.1.9.dist-info/RECORD
