Metadata-Version: 2.1
Name: limber
Version: 0.1.9
Summary: Serverless DAGs orchestrated via Python
Home-page: https://github.com/StijnZanders/limber
Author: Stijn Zanders
Author-email: zandersstijn@gmail.com
License: UNKNOWN
Platform: UNKNOWN
Classifier: Programming Language :: Python :: 3
Classifier: License :: OSI Approved :: Apache Software License
Classifier: Operating System :: OS Independent
License-File: LICENSE
Requires-Dist: cdktf (==0.7.0)
Requires-Dist: click (==8.0.3)
Requires-Dist: google-cloud-pubsub (==2.8.0)
Requires-Dist: google-cloud (==0.34.0)
